stuff/__init__.py
stuff-0.0.0.dev0.dist-info/LICENSE.rst
stuff-0.0.0.dev0.dist-info/METADATA
stuff-0.0.0.dev0.dist-info/WHEEL
stuff-0.0.0.dev0.dist-info/top_level.txt
stuff-0.0.0.dev0.dist-info/RECORD
