Metadata-Version: 2.1
Name: stuff
Version: 0.0.0.dev0
Summary: Stuff 'n' Things
Home-page: https://github.com/simplistix/stuff
Author: Chris Withers
Author-email: chris@withers.org
License: MIT
Platform: UNKNOWN
Classifier: License :: OSI Approved :: MIT License
Classifier: Programming Language :: Python :: 3
Classifier: Programming Language :: Python :: 3.6
Classifier: Programming Language :: Python :: 3.9
License-File: LICENSE.rst
Provides-Extra: build
Requires-Dist: furo ; extra == 'build'
Requires-Dist: sphinx ; extra == 'build'
Requires-Dist: setuptools-git ; extra == 'build'
Requires-Dist: twine ; extra == 'build'
Requires-Dist: wheel ; extra == 'build'
Provides-Extra: test
Requires-Dist: pytest ; extra == 'test'
Requires-Dist: pytest-cov ; extra == 'test'
Requires-Dist: sybil ; extra == 'test'
Requires-Dist: testfixtures ; extra == 'test'
